odoo/addons/sale_loyalty_order_suggestion_multi_gift/README.rst
odoo/addons/sale_loyalty_order_suggestion_multi_gift/__init__.py
odoo/addons/sale_loyalty_order_suggestion_multi_gift/__manifest__.py
odoo/addons/sale_loyalty_order_suggestion_multi_gift/i18n/it.po
odoo/addons/sale_loyalty_order_suggestion_multi_gift/i18n/sale_loyalty_order_suggestion_multi_gift.pot
odoo/addons/sale_loyalty_order_suggestion_multi_gift/models/__init__.py
odoo/addons/sale_loyalty_order_suggestion_multi_gift/models/sale_order.py
odoo/addons/sale_loyalty_order_suggestion_multi_gift/readme/CONTRIBUTORS.md
odoo/addons/sale_loyalty_order_suggestion_multi_gift/readme/DESCRIPTION.md
odoo/addons/sale_loyalty_order_suggestion_multi_gift/readme/ROADMAP.md
odoo/addons/sale_loyalty_order_suggestion_multi_gift/readme/USAGE.md
odoo/addons/sale_loyalty_order_suggestion_multi_gift/static/description/icon.png
odoo/addons/sale_loyalty_order_suggestion_multi_gift/static/description/index.html
odoo/addons/sale_loyalty_order_suggestion_multi_gift/tests/__init__.py
odoo/addons/sale_loyalty_order_suggestion_multi_gift/tests/test_sale_loyalty_order_suggestion_multi_gift.py
odoo/addons/sale_loyalty_order_suggestion_multi_gift/wizard/__init__.py
odoo/addons/sale_loyalty_order_suggestion_multi_gift/wizard/sale_loyalty_reward_wizard.py
odoo_addon_sale_loyalty_order_suggestion_multi_gift-18.0.1.0.1.dist-info/METADATA
odoo_addon_sale_loyalty_order_suggestion_multi_gift-18.0.1.0.1.dist-info/WHEEL
odoo_addon_sale_loyalty_order_suggestion_multi_gift-18.0.1.0.1.dist-info/top_level.txt
odoo_addon_sale_loyalty_order_suggestion_multi_gift-18.0.1.0.1.dist-info/RECORD
